Workbook

Sheet Dashboard
B2: Marcela Pool Loan Tracker
B3: Lender. Brendan T. O'Connor | Borrower. Marcela Arenas | Effective May 2, 2025
B5: LOAN TERMS | E5: CURRENT STATUS
B6: Original Principal | C6: 50000 | E6: Payments Made | F6: =COUNT('Payment Register'!C7:C200) -> 15
B7: Annual Interest Rate | C7: 0.05 | E7: Payments Remaining | F7: =C8-F6 -> 69
B8: Term (Months) | C8: 84 | E8: Total Paid to Date | F8: =SUMIF('Payment Register'!C7:C200,">0",'Payment Register'!D7:D200) -> 52724.51
B9: Funded Date | C9: 45763 | E9: Total Interest Accrued | F9: =SUMIF('Payment Register'!C7:C200,">0",'Payment Register'!F7:F200) -> 2724.51
B10: First Payment Date | C10: 45812 | E10: Total Interest Paid | F10: =SUMIF('Payment Register'!C7:C200,">0",'Payment Register'!F7:F200) -> 2724.51
B11: Maturity Date | C11: 48336 | E11: Total Principal Paid | F11: =SUMIF('Payment Register'!C7:C200,">0",'Payment Register'!G7:G200) -> 50000
B12: Original Monthly Payment | C12: 706.7 | E12: Current Principal Balance | F12: =LOOKUP(2,1/('Payment Register'!H6:H200<>""),'Payment Register'!H6:H200) -> 0
E15: Required Next Payment | F15: =IF(F12<=0,0,IF(F7<=0,F12,-PMT(C7/12,F7,F12))) -> 0
E16: Variance vs Expected Schedule | F16: =IF(F6=0,0,F12-INDEX('Expected Schedule'!G6:G89,MIN(F6,84))) -> -42302.47
B18: § 1.5 PREPAYMENT NOTE
B19: If Marcela makes a lump sum prepayment, log it in the Payment Register with Type set to 'Lump Sum'. The 'Required Next Payment' above will auto-recalculate using the remaining principal, 5% annual rate, and remaining months to maturity. Per § 1.5, you must provide written notice of the adjusted monthly payment within 15 days of the prepayment.
B23: HOW TO USE
B24: 1. Type Date and Amount in the next blank row of the Payment Register. Everything else auto-fills.
B25: 2. Interest accrues monthly at 5%/12 on prior balance, regardless of exact payment date.
B26: 3. For lump sum payments, set Type to 'Lump Sum'. Required Next Payment on this dashboard updates immediately.
B27: 4. The BofA auto-import cron runs on the 7th of each month and appends new Zelle deposits automatically.
B28: 5. Bookmark the OneDrive URL for one-click access. Auto-save preserves every edit.
B30: PAYOFF QUOTE
B31: Live payoff calculation. Change the Payoff Date input to reprice for any future date.
B32: Payoff Date | C32: 46220 | E32: Per Diem Interest | F32: =ROUND(C34*C7/365,4) -> 0
B33: Next Scheduled Due Date | C33: =DATE(2026,8,5) -> 46239 | E33: Accrued Interest (Actual/365) | F33: =IF(C35="","",ROUND(C34*C7/365*C35,2)) -> 0
B34: Principal Balance | C34: =F12 -> 0 | E34: Total Payoff Amount | F34: =IF(F33="","",C34+F33) -> 0
B35: Days Accrued Since Due Date | C35: =IF(OR(C32="",C33=""),"",MAX(0,C32-C33)) -> 0 | E35: Interest Saved vs. Maturity | F35: =IF(F34="","",ROUND(F7*C12-F34,2)) -> 48762.3
B37: Method. 5.00% APR fixed, actual/365 daily accrual on outstanding principal. Payment #14 (received 6/29/2026, memo "Pool loan payment July 1 2026") satisfied the July 5, 2026 installment early, so no interest accrues for a payoff on or before the next scheduled due date of August 5, 2026. No prepayment penalty. Payoff quote reissued 7/16/2026.

Sheet Payment Register
B2: Payment Register
B3: Monthly accrual cycle. Each row charges one month of interest at 5%/12 on prior balance starting from the funded date. Borrower has been on schedule since first payment 6/4/25.
B5: Pmt # | C5: Date | D5: Amount Received | E5: Type | F5: Interest | G5: Principal | H5: Balance | I5: Notes
B6: 0 | C6: 45763 | E6: Origination | H6: =Dashboard!C6 -> 50000 | I6: Loan funded via Fidelity wire on or about 4/16/25.
B7: =IF(C7="","",MAX($B$6:B6)+1) -> 1 | C7: 45812 | D7: 706.7 | E7: Regular | F7: =IF(C7="","",ROUND(H6*Dashboard!$C$7/12,2)) -> 208.33 | G7: =IF(C7="","",IF(OR(D7="",ISBLANK(D7)),-F7,D7-F7)) -> 498.37 | H7: =IF(C7="",H6,H6-G7) -> 49501.63 | I7: KeyBank Zelle. Conf# OB619HFDC. First payment, made to Key Privilege Checking ending 5597.
B8: =IF(C8="","",MAX($B$6:B7)+1) -> 2 | C8: 45845 | D8: 706.7 | E8: Regular | F8: =IF(C8="","",ROUND(H7*Dashboard!$C$7/12,2)) -> 206.26 | G8: =IF(C8="","",IF(OR(D8="",ISBLANK(D8)),-F8,D8-F8)) -> 500.44 | H8: =IF(C8="",H7,H7-G8) -> 49001.19 | I8: KeyBank Zelle. Conf# WBA1I7DAC.
B9: =IF(C9="","",MAX($B$6:B8)+1) -> 3 | C9: 45870 | D9: 706.7 | E9: Regular | F9: =IF(C9="","",ROUND(H8*Dashboard!$C$7/12,2)) -> 204.17 | G9: =IF(C9="","",IF(OR(D9="",ISBLANK(D9)),-F9,D9-F9)) -> 502.53 | H9: =IF(C9="",H8,H8-G9) -> 48498.66 | I9: KeyBank Zelle. Conf# LB21W76VC.
B10: =IF(C10="","",MAX($B$6:B9)+1) -> 4 | C10: 45902 | D10: 706.7 | E10: Regular | F10: =IF(C10="","",ROUND(H9*Dashboard!$C$7/12,2)) -> 202.08 | G10: =IF(C10="","",IF(OR(D10="",ISBLANK(D10)),-F10,D10-F10)) -> 504.62 | H10: =IF(C10="",H9,H9-G10) -> 47994.04 | I10: KeyBank Zelle. Conf# 9BJ1SIXYC. Final KeyBank payment before switch to BofA.
B11: =IF(C11="","",MAX($B$6:B10)+1) -> 5 | C11: 45931 | D11: 706.7 | E11: Regular | F11: =IF(C11="","",ROUND(H10*Dashboard!$C$7/12,2)) -> 199.98 | G11: =IF(C11="","",IF(OR(D11="",ISBLANK(D11)),-F11,D11-F11)) -> 506.72 | H11: =IF(C11="",H10,H10-G11) -> 47487.32 | I11: First BofA payment. Conf# (see prior register).
B12: =IF(C12="","",MAX($B$6:B11)+1) -> 6 | C12: 45964 | D12: 706.7 | E12: Regular | F12: =IF(C12="","",ROUND(H11*Dashboard!$C$7/12,2)) -> 197.86 | G12: =IF(C12="","",IF(OR(D12="",ISBLANK(D12)),-F12,D12-F12)) -> 508.84 | H12: =IF(C12="",H11,H11-G12) -> 46978.48 | I12: BofA. Memo 'Pool'. Conf# 0JIZRC3U8.
B13: =IF(C13="","",MAX($B$6:B12)+1) -> 7 | C13: 45992 | D13: 706.7 | E13: Regular | F13: =IF(C13="","",ROUND(H12*Dashboard!$C$7/12,2)) -> 195.74 | G13: =IF(C13="","",IF(OR(D13="",ISBLANK(D13)),-F13,D13-F13)) -> 510.96 | H13: =IF(C13="",H12,H12-G13) -> 46467.52 | I13: BofA. Memo 'Loan payment'. Conf# 0JJRGLOB7.
B14: =IF(C14="","",MAX($B$6:B13)+1) -> 8 | C14: 46024 | D14: 706.7 | E14: Regular | F14: =IF(C14="","",ROUND(H13*Dashboard!$C$7/12,2)) -> 193.61 | G14: =IF(C14="","",IF(OR(D14="",ISBLANK(D14)),-F14,D14-F14)) -> 513.09 | H14: =IF(C14="",H13,H13-G14) -> 45954.43 | I14: BofA. Memo 'Loan payment'. Conf# 007AM25CP.
B15: =IF(C15="","",MAX($B$6:B14)+1) -> 9 | C15: 46055 | D15: 706.7 | E15: Regular | F15: =IF(C15="","",ROUND(H14*Dashboard!$C$7/12,2)) -> 191.48 | G15: =IF(C15="","",IF(OR(D15="",ISBLANK(D15)),-F15,D15-F15)) -> 515.22 | H15: =IF(C15="",H14,H14-G15) -> 45439.21 | I15: BofA. Memo 'Loan payment'. Conf# 0215E4F30.
B16: =IF(C16="","",MAX($B$6:B15)+1) -> 10 | C16: 46083 | D16: 706.7 | E16: Regular | F16: =IF(C16="","",ROUND(H15*Dashboard!$C$7/12,2)) -> 189.33 | G16: =IF(C16="","",IF(OR(D16="",ISBLANK(D16)),-F16,D16-F16)) -> 517.37 | H16: =IF(C16="",H15,H15-G16) -> 44921.84 | I16: BofA. Memo 'Pool loan payment'. Conf# 021XHGEY7.
B17: =IF(C17="","",MAX($B$6:B16)+1) -> 11 | C17: 46113 | D17: 706.7 | E17: Regular | F17: =IF(C17="","",ROUND(H16*Dashboard!$C$7/12,2)) -> 187.17 | G17: =IF(C17="","",IF(OR(D17="",ISBLANK(D17)),-F17,D17-F17)) -> 519.53 | H17: =IF(C17="",H16,H16-G17) -> 44402.31 | I17: BofA. No memo. Conf# 022RBAIMR.
B18: =IF(C18="","",MAX($B$6:B17)+1) -> 12 | C18: 46143 | D18: 706.7 | E18: Regular | F18: =IF(C18="","",ROUND(H17*Dashboard!$C$7/12,2)) -> 185.01 | G18: =IF(C18="","",IF(OR(D18="",ISBLANK(D18)),-F18,D18-F18)) -> 521.69 | H18: =IF(C18="",H17,H17-G18) -> 43880.62 | I18: BofA. Memo 'Pool payment'. Conf# 0K5LIHSOY.
... B20: =IF(C20="","",MAX($B$6:B19)+1) -> 14 | C20: 46202 | D20: 706.7 | E20: Regular | F20: =IF(C20="","",ROUND(H19*Dashboard!$C$7/12,2)) -> 180.65 | G20: =IF(C20="","",IF(OR(D20="",ISBLANK(D20)),-F20,D20-F20)) -> 526.05 | H20: =IF(C20="",H19,H19-G20) -> 42830.71 | I20: Auto-imported. Conf# 0K788773T. Memo: Pool loan payment July 1 2026 (paid early 6/29)
B21: =IF(C21="","",MAX($B$6:B20)+1) -> 15 | C21: 46222 | D21: 42830.71 | E21: Payoff | F21: 0 | G21: =IF(C21="","",IF(OR(D21="",ISBLANK(D21)),-F21,D21-F21)) -> 42830.71 | H21: =IF(C21="",H20,H20-G21) -> 0 | I21: PAID IN FULL. Chase check #502 dated 7/19/2026, deposited BofA Fruitville Rd 7/21/2026, BofA Trans #5628. Paid before August accrual date, so no interest accrued after 6/29 payment.
B22: =IF(C22="","",MAX($B$6:B21)+1) | F22: =IF(C22="","",ROUND(H21*Dashboard!$C$7/12,2)) | G22: =IF(C22="","",IF(OR(D22="",ISBLANK(D22)),-F22,D22-F22)) | H22: =IF(C22="",H21,H21-G22) -> 0
B23: =IF(C23="","",MAX($B$6:B22)+1) | F23: =IF(C23="","",ROUND(H22*Dashboard!$C$7/12,2)) | G23: =IF(C23="","",IF(OR(D23="",ISBLANK(D23)),-F23,D23-F23)) | H23: =IF(C23="",H22,H22-G23) -> 0
B24: =IF(C24="","",MAX($B$6:B23)+1) | F24: =IF(C24="","",ROUND(H23*Dashboard!$C$7/12,2)) | G24: =IF(C24="","",IF(OR(D24="",ISBLANK(D24)),-F24,D24-F24)) | H24: =IF(C24="",H23,H23-G24) -> 0
B25: =IF(C25="","",MAX($B$6:B24)+1) | F25: =IF(C25="","",ROUND(H24*Dashboard!$C$7/12,2)) | G25: =IF(C25="","",IF(OR(D25="",ISBLANK(D25)),-F25,D25-F25)) | H25: =IF(C25="",H24,H24-G25) -> 0
B26: =IF(C26="","",MAX($B$6:B25)+1) | F26: =IF(C26="","",ROUND(H25*Dashboard!$C$7/12,2)) | G26: =IF(C26="","",IF(OR(D26="",ISBLANK(D26)),-F26,D26-F26)) | H26: =IF(C26="",H25,H25-G26) -> 0
B27: =IF(C27="","",MAX($B$6:B26)+1) | F27: =IF(C27="","",ROUND(H26*Dashboard!$C$7/12,2)) | G27: =IF(C27="","",IF(OR(D27="",ISBLANK(D27)),-F27,D27-F27)) | H27: =IF(C27="",H26,H26-G27) -> 0
B28: =IF(C28="","",MAX($B$6:B27)+1) | F28: =IF(C28="","",ROUND(H27*Dashboard!$C$7/12,2)) | G28: =IF(C28="","",IF(OR(D28="",ISBLANK(D28)),-F28,D28-F28)) | H28: =IF(C28="",H27,H27-G28) -> 0
B29: =IF(C29="","",MAX($B$6:B28)+1) | F29: =IF(C29="","",ROUND(H28*Dashboard!$C$7/12,2)) | G29: =IF(C29="","",IF(OR(D29="",ISBLANK(D29)),-F29,D29-F29)) | H29: =IF(C29="",H28,H28-G29) -> 0
B30: =IF(C30="","",MAX($B$6:B29)+1) | F30: =IF(C30="","",ROUND(H29*Dashboard!$C$7/12,2)) | G30: =IF(C30="","",IF(OR(D30="",ISBLANK(D30)),-F30,D30-F30)) | H30: =IF(C30="",H29,H29-G30) -> 0
B31: =IF(C31="","",MAX($B$6:B30)+1) | F31: =IF(C31="","",ROUND(H30*Dashboard!$C$7/12,2)) | G31: =IF(C31="","",IF(OR(D31="",ISBLANK(D31)),-F31,D31-F31)) | H31: =IF(C31="",H30,H30-G31) -> 0
B32: =IF(C32="","",MAX($B$6:B31)+1) | F32: =IF(C32="","",ROUND(H31*Dashboard!$C$7/12,2)) | G32: =IF(C32="","",IF(OR(D32="",ISBLANK(D32)),-F32,D32-F32)) | H32: =IF(C32="",H31,H31-G32) -> 0
B33: =IF(C33="","",MAX($B$6:B32)+1) | F33: =IF(C33="","",ROUND(H32*Dashboard!$C$7/12,2)) | G33: =IF(C33="","",IF(OR(D33="",ISBLANK(D33)),-F33,D33-F33)) | H33: =IF(C33="",H32,H32-G33) -> 0
... B200: =IF(C200="","",MAX($B$6:B199)+1) | F200: =IF(C200="","",ROUND(H199*Dashboard!$C$7/12,2)) | G200: =IF(C200="","",IF(OR(D200="",ISBLANK(D200)),-F200,D200-F200)) | H200: =IF(C200="",H199,H199-G200) -> 0

Sheet Expected Schedule
B2: Expected Payment Schedule (84 Months, Payments Due 5th of Month)
B3: Reflects expected monthly payments of $706.70 from the Effective Loan Start (9/1/25). Compare against actual register.
B5: Pmt # | C5: Date | D5: Payment | E5: Interest | F5: Principal | G5: Balance
B6: 1 | C6: 45935 | D6: 706.7 | E6: 208.33 | F6: 498.37 | G6: 49501.63
B7: 2 | C7: 45966 | D7: 706.7 | E7: 206.26 | F7: 500.44 | G7: 49001.19
B8: 3 | C8: 45996 | D8: 706.7 | E8: 204.17 | F8: 502.53 | G8: 48498.66
B9: 4 | C9: 46027 | D9: 706.7 | E9: 202.08 | F9: 504.62 | G9: 47994.04
B10: 5 | C10: 46058 | D10: 706.7 | E10: 199.98 | F10: 506.72 | G10: 47487.32
B11: 6 | C11: 46086 | D11: 706.7 | E11: 197.86 | F11: 508.84 | G11: 46978.48
B12: 7 | C12: 46117 | D12: 706.7 | E12: 195.74 | F12: 510.96 | G12: 46467.52
B13: 8 | C13: 46147 | D13: 706.7 | E13: 193.61 | F13: 513.09 | G13: 45954.43
B14: 9 | C14: 46178 | D14: 706.7 | E14: 191.48 | F14: 515.22 | G14: 45439.21
B15: 10 | C15: 46208 | D15: 706.7 | E15: 189.33 | F15: 517.37 | G15: 44921.84
B16: 11 | C16: 46239 | D16: 706.7 | E16: 187.17 | F16: 519.53 | G16: 44402.31
B17: 12 | C17: 46270 | D17: 706.7 | E17: 185.01 | F17: 521.69 | G17: 43880.62
... B89: 84 | C89: 48462 | D89: 706.24 | E89: 2.93 | F89: 703.31 | G89: 0
